lonelyguy/__about__.py
lonelyguy/__init__.py
lonelyguy/__main__.py
lonelyguy-0.0.2.dist-info/METADATA
lonelyguy-0.0.2.dist-info/WHEEL
lonelyguy-0.0.2.dist-info/entry_points.txt
lonelyguy-0.0.2.dist-info/licenses/LICENSE.txt
lonelyguy-0.0.2.dist-info/RECORD
