Metadata-Version: 2.4
Name: lonelyguy
Version: 0.0.2
Summary: A simple command-line tool to open a predefined set of URLs in a web browser.
Project-URL: Documentation, https://github.com/lonelyguy12/lonelyguy#readme
Project-URL: Issues, https://github.com/lonelyguy12/lonelyguy/issues
Project-URL: Source, https://github.com/lonelyguy12/lonelyguy
Author-email: Lonely Guy <phoenex659@gmail.com>
License-Expression: MIT
License-File: LICENSE.txt
Keywords: automation,cli,opener,url
Classifier: Development Status :: 4 - Beta
Classifier: Programming Language :: Python
Classifier: Programming Language :: Python :: 3.8
Classifier: Programming Language :: Python :: 3.9
Classifier: Programming Language :: Python :: 3.10
Classifier: Programming Language :: Python :: 3.11
Classifier: Programming Language :: Python :: 3.12
Classifier: Programming Language :: Python :: Implementation :: CPython
Classifier: Programming Language :: Python :: Implementation :: PyPy
Requires-Python: >=3.8
